[
    {
        "fecha": "11-02-2026",
        "etapas": [
            {
                "area": "F2",
                "total": 1000,
                "tipoAlimento": "Hibrido",
                "cantidadKg": 799.244
            }
        ]
    },
    {
        "fecha": "12-02-2026",
        "etapas": [
            {
                "area": "F2",
                "total": 1000,
                "tipoAlimento": "Hibrido",
                "cantidadKg": 804.484
            }
        ]
    },
    {
        "fecha": "13-02-2026",
        "etapas": [
            {
                "area": "F2",
                "total": 1000,
                "tipoAlimento": "Hibrido",
                "cantidadKg": 806.797
            }
        ]
    },
    {
        "fecha": "14-02-2026",
        "etapas": [
            {
                "area": "F2",
                "total": 1000,
                "tipoAlimento": "Hibrido",
                "cantidadKg": 805.871
            }
        ]
    },
    {
        "fecha": "15-02-2026",
        "etapas": [
            {
                "area": "F2",
                "total": 1000,
                "tipoAlimento": "Hibrido",
                "cantidadKg": 803.655
            }
        ]
    },
    {
        "fecha": "16-02-2026",
        "etapas": [
            {
                "area": "F2",
                "total": 1000,
                "tipoAlimento": "Hibrido",
                "cantidadKg": 801.914
            }
        ]
    },
    {
        "fecha": "17-02-2026",
        "etapas": [
            {
                "area": "F2",
                "total": 1000,
                "tipoAlimento": "Hibrido",
                "cantidadKg": 807.271
            }
        ]
    },
    {
        "fecha": "18-02-2026",
        "etapas": [
            {
                "area": "F2",
                "total": 1000,
                "tipoAlimento": "Hibrido",
                "cantidadKg": 810.915
            }
        ]
    },
    {
        "fecha": "19-02-2026",
        "etapas": [
            {
                "area": "F2",
                "total": 1000,
                "tipoAlimento": "Solido1",
                "cantidadKg": 1803.197
            }
        ]
    },
    {
        "fecha": "20-02-2026",
        "etapas": [
            {
                "area": "F2",
                "total": 1000,
                "tipoAlimento": "Solido1",
                "cantidadKg": 1803.661
            }
        ]
    },
    {
        "fecha": "21-02-2026",
        "etapas": [
            {
                "area": "F2",
                "total": 1000,
                "tipoAlimento": "Solido1",
                "cantidadKg": 1800.794
            }
        ]
    },
    {
        "fecha": "22-02-2026",
        "etapas": [
            {
                "area": "F2",
                "total": 1000,
                "tipoAlimento": "Solido1",
                "cantidadKg": 1799.427
            }
        ]
    },
    {
        "fecha": "23-02-2026",
        "etapas": [
            {
                "area": "F2",
                "total": 1000,
                "tipoAlimento": "Solido1",
                "cantidadKg": 1802.43
            }
        ]
    },
    {
        "fecha": "24-02-2026",
        "etapas": [
            {
                "area": "F2",
                "total": 1000,
                "tipoAlimento": "Solido1",
                "cantidadKg": 1802.115
            }
        ]
    },
    {
        "fecha": "25-02-2026",
        "etapas": [
            {
                "area": "F2",
                "total": 1000,
                "tipoAlimento": "Solido1",
                "cantidadKg": 1804.812
            }
        ]
    },
    {
        "fecha": "26-02-2026",
        "etapas": [
            {
                "area": "F2",
                "total": 1000,
                "tipoAlimento": "Solido1",
                "cantidadKg": 1796.038
            }
        ]
    },
    {
        "fecha": "27-02-2026",
        "etapas": [
            {
                "area": "F2",
                "total": 1000,
                "tipoAlimento": "Solido1",
                "cantidadKg": 1797.796
            }
        ]
    },
    {
        "fecha": "28-02-2026",
        "etapas": [
            {
                "area": "F2",
                "total": 1000,
                "tipoAlimento": "Solido1",
                "cantidadKg": 1801.455
            }
        ]
    },
    {
        "fecha": "01-03-2026",
        "etapas": [
            {
                "area": "F2",
                "total": 1000,
                "tipoAlimento": "Solido1",
                "cantidadKg": 1794.857
            }
        ]
    },
    {
        "fecha": "02-03-2026",
        "etapas": [
            {
                "area": "F2",
                "total": 1000,
                "tipoAlimento": "Solido1",
                "cantidadKg": 1796.305
            }
        ]
    },
    {
        "fecha": "03-03-2026",
        "etapas": [
            {
                "area": "F2",
                "total": 1000,
                "tipoAlimento": "Solido1",
                "cantidadKg": 1796.931
            }
        ]
    },
    {
        "fecha": "04-03-2026",
        "etapas": [
            {
                "area": "F2",
                "total": 1000,
                "tipoAlimento": "Solido1",
                "cantidadKg": 1793.731
            }
        ]
    },
    {
        "fecha": "05-03-2026",
        "etapas": [
            {
                "area": "F2",
                "total": 1000,
                "tipoAlimento": "Solido1",
                "cantidadKg": 1801.928
            }
        ]
    },
    {
        "fecha": "06-03-2026",
        "etapas": [
            {
                "area": "F2",
                "total": 1000,
                "tipoAlimento": "Solido1",
                "cantidadKg": 1799.123
            }
        ]
    },
    {
        "fecha": "07-03-2026",
        "etapas": [
            {
                "area": "F2",
                "total": 1000,
                "tipoAlimento": "Solido1",
                "cantidadKg": 1800.818
            }
        ]
    },
    {
        "fecha": "08-03-2026",
        "etapas": [
            {
                "area": "F2",
                "total": 1000,
                "tipoAlimento": "Solido1",
                "cantidadKg": 1797.223
            }
        ]
    },
    {
        "fecha": "09-03-2026",
        "etapas": [
            {
                "area": "F2",
                "total": 1000,
                "tipoAlimento": "Solido1",
                "cantidadKg": 1799.838
            }
        ]
    },
    {
        "fecha": "10-03-2026",
        "etapas": [
            {
                "area": "F2",
                "total": 1000,
                "tipoAlimento": "Solido1",
                "cantidadKg": 1803.177
            }
        ]
    },
    {
        "fecha": "11-03-2026",
        "etapas": [
            {
                "area": "F2",
                "total": 1000,
                "tipoAlimento": "Solido1",
                "cantidadKg": 1797.164
            }
        ]
    },
    {
        "fecha": "12-03-2026",
        "etapas": [
            {
                "area": "F2",
                "total": 1000,
                "tipoAlimento": "Solido1",
                "cantidadKg": 1797.35
            }
        ]
    },
    {
        "fecha": "13-03-2026",
        "etapas": [
            {
                "area": "F2",
                "total": 1000,
                "tipoAlimento": "Solido1",
                "cantidadKg": 1794.955
            }
        ]
    },
    {
        "fecha": "14-03-2026",
        "etapas": [
            {
                "area": "F2",
                "total": 1000,
                "tipoAlimento": "Solido1",
                "cantidadKg": 1799.537
            }
        ]
    },
    {
        "fecha": "15-03-2026",
        "etapas": [
            {
                "area": "F2",
                "total": 1000,
                "tipoAlimento": "Solido1",
                "cantidadKg": 1800.602
            }
        ]
    },
    {
        "fecha": "16-03-2026",
        "etapas": [
            {
                "area": "F2",
                "total": 1000,
                "tipoAlimento": "Solido1",
                "cantidadKg": 1796.447
            }
        ]
    },
    {
        "fecha": "17-03-2026",
        "etapas": [
            {
                "area": "F2",
                "total": 1000,
                "tipoAlimento": "Solido1",
                "cantidadKg": 1797.91
            }
        ]
    },
    {
        "fecha": "18-03-2026",
        "etapas": [
            {
                "area": "F2",
                "total": 1000,
                "tipoAlimento": "Solido1",
                "cantidadKg": 1794.298
            }
        ]
    },
    {
        "fecha": "19-03-2026",
        "etapas": [
            {
                "area": "F2",
                "total": 1000,
                "tipoAlimento": "Solido1",
                "cantidadKg": 1798.978
            }
        ]
    },
    {
        "fecha": "20-03-2026",
        "etapas": [
            {
                "area": "F2",
                "total": 1000,
                "tipoAlimento": "Solido1",
                "cantidadKg": 1800.414
            }
        ]
    },
    {
        "fecha": "21-03-2026",
        "etapas": [
            {
                "area": "F2",
                "total": 1000,
                "tipoAlimento": "Solido1",
                "cantidadKg": 1793.65
            }
        ]
    },
    {
        "fecha": "22-03-2026",
        "etapas": [
            {
                "area": "F2",
                "total": 1000,
                "tipoAlimento": "Solido1",
                "cantidadKg": 1799.001
            }
        ]
    },
    {
        "fecha": "23-03-2026",
        "etapas": [
            {
                "area": "F2",
                "total": 1000,
                "tipoAlimento": "Solido1",
                "cantidadKg": 1801.217
            }
        ]
    },
    {
        "fecha": "24-03-2026",
        "etapas": [
            {
                "area": "F2",
                "total": 1000,
                "tipoAlimento": "Solido1",
                "cantidadKg": 1800.173
            }
        ]
    },
    {
        "fecha": "25-03-2026",
        "etapas": [
            {
                "area": "F2",
                "total": 1000,
                "tipoAlimento": "Solido1",
                "cantidadKg": 1802.882
            }
        ]
    },
    {
        "fecha": "26-03-2026",
        "etapas": [
            {
                "area": "F2",
                "total": 1000,
                "tipoAlimento": "Solido1",
                "cantidadKg": 1800.592
            }
        ]
    },
    {
        "fecha": "27-03-2026",
        "etapas": [
            {
                "area": "F2",
                "total": 1000,
                "tipoAlimento": "Solido1",
                "cantidadKg": 1804.935
            }
        ]
    },
    {
        "fecha": "28-03-2026",
        "etapas": [
            {
                "area": "F2",
                "total": 1000,
                "tipoAlimento": "Solido1",
                "cantidadKg": 1800.628
            }
        ]
    },
    {
        "fecha": "29-03-2026",
        "etapas": [
            {
                "area": "F2",
                "total": 1000,
                "tipoAlimento": "Solido1",
                "cantidadKg": 1797.831
            }
        ]
    },
    {
        "fecha": "30-03-2026",
        "etapas": [
            {
                "area": "F2",
                "total": 1000,
                "tipoAlimento": "Solido1",
                "cantidadKg": 1803.044
            }
        ]
    },
    {
        "fecha": "31-03-2026",
        "etapas": [
            {
                "area": "F2",
                "total": 1000,
                "tipoAlimento": "Solido1",
                "cantidadKg": 1800.472
            }
        ]
    },
    {
        "fecha": "01-04-2026",
        "etapas": [
            {
                "area": "F2",
                "total": 1000,
                "tipoAlimento": "Solido1",
                "cantidadKg": 1799.248
            }
        ]
    },
    {
        "fecha": "02-04-2026",
        "etapas": [
            {
                "area": "F2",
                "total": 1000,
                "tipoAlimento": "Solido1",
                "cantidadKg": 1800.975
            }
        ]
    },
    {
        "fecha": "03-04-2026",
        "etapas": [
            {
                "area": "F2",
                "total": 1000,
                "tipoAlimento": "Solido1",
                "cantidadKg": 1801.452
            }
        ]
    },
    {
        "fecha": "04-04-2026",
        "etapas": [
            {
                "area": "F2",
                "total": 1000,
                "tipoAlimento": "Solido1",
                "cantidadKg": 1799.893
            }
        ]
    },
    {
        "fecha": "05-04-2026",
        "etapas": [
            {
                "area": "F2",
                "total": 1000,
                "tipoAlimento": "Solido1",
                "cantidadKg": 1795.998
            }
        ]
    },
    {
        "fecha": "06-04-2026",
        "etapas": [
            {
                "area": "F2",
                "total": 1000,
                "tipoAlimento": "Solido1",
                "cantidadKg": 1804.724
            }
        ]
    },
    {
        "fecha": "07-04-2026",
        "etapas": [
            {
                "area": "F2",
                "total": 1000,
                "tipoAlimento": "Solido1",
                "cantidadKg": 1802.192
            }
        ]
    },
    {
        "fecha": "08-04-2026",
        "etapas": [
            {
                "area": "F2",
                "total": 1000,
                "tipoAlimento": "Solido1",
                "cantidadKg": 1796.805
            }
        ]
    },
    {
        "fecha": "09-04-2026",
        "etapas": [
            {
                "area": "F2",
                "total": 1000,
                "tipoAlimento": "Solido1",
                "cantidadKg": 1796.091
            }
        ]
    },
    {
        "fecha": "10-04-2026",
        "etapas": [
            {
                "area": "F2",
                "total": 1000,
                "tipoAlimento": "Solido1",
                "cantidadKg": 1798.011
            }
        ]
    },
    {
        "fecha": "11-04-2026",
        "etapas": [
            {
                "area": "F2",
                "total": 1000,
                "tipoAlimento": "Solido1",
                "cantidadKg": 1796.495
            }
        ]
    },
    {
        "fecha": "12-04-2026",
        "etapas": [
            {
                "area": "F2",
                "total": 1000,
                "tipoAlimento": "Solido1",
                "cantidadKg": 1801.916
            }
        ]
    },
    {
        "fecha": "13-04-2026",
        "etapas": [
            {
                "area": "F2",
                "total": 1000,
                "tipoAlimento": "Solido1",
                "cantidadKg": 1797.658
            }
        ]
    },
    {
        "fecha": "14-04-2026",
        "etapas": [
            {
                "area": "F2",
                "total": 1000,
                "tipoAlimento": "Solido1",
                "cantidadKg": 1801.729
            }
        ]
    },
    {
        "fecha": "15-04-2026",
        "etapas": [
            {
                "area": "F2",
                "total": 1000,
                "tipoAlimento": "Solido1",
                "cantidadKg": 1800.204
            }
        ]
    },
    {
        "fecha": "16-04-2026",
        "etapas": [
            {
                "area": "F2",
                "total": 1000,
                "tipoAlimento": "Solido1",
                "cantidadKg": 1798.5720000000001
            }
        ]
    },
    {
        "fecha": "17-04-2026",
        "etapas": [
            {
                "area": "F2",
                "total": 1000,
                "tipoAlimento": "Solido1",
                "cantidadKg": 1800.806
            }
        ]
    },
    {
        "fecha": "18-04-2026",
        "etapas": [
            {
                "area": "F2",
                "total": 1000,
                "tipoAlimento": "Solido1",
                "cantidadKg": 1803.055
            }
        ]
    },
    {
        "fecha": "19-04-2026",
        "etapas": [
            {
                "area": "F2",
                "total": 1000,
                "tipoAlimento": "Solido1",
                "cantidadKg": 1802.045
            }
        ]
    },
    {
        "fecha": "20-04-2026",
        "etapas": [
            {
                "area": "F2",
                "total": 1000,
                "tipoAlimento": "Solido1",
                "cantidadKg": 1797.365
            }
        ]
    },
    {
        "fecha": "21-04-2026",
        "etapas": [
            {
                "area": "F2",
                "total": 1000,
                "tipoAlimento": "Solido1",
                "cantidadKg": 1803.571
            }
        ]
    },
    {
        "fecha": "22-04-2026",
        "etapas": [
            {
                "area": "F2",
                "total": 1000,
                "tipoAlimento": "Solido1",
                "cantidadKg": 1798.869
            }
        ]
    },
    {
        "fecha": "23-04-2026",
        "etapas": [
            {
                "area": "F2",
                "total": 1000,
                "tipoAlimento": "Solido1",
                "cantidadKg": 1801.488
            }
        ]
    }
]